query_counter/__init__.py
query_counter/apps.py
query_counter/decorators.py
query_counter/middleware.py
query_counter/settings.py
django_query_counter-0.4.2.dist-info/METADATA
django_query_counter-0.4.2.dist-info/WHEEL
django_query_counter-0.4.2.dist-info/licenses/AUTHORS.md
django_query_counter-0.4.2.dist-info/licenses/LICENSE
django_query_counter-0.4.2.dist-info/RECORD
